pecheny_utils/__init__.py
pecheny_utils/version.py
pecheny_utils-0.0.8.dist-info/._PKG-INFO
pecheny_utils-0.0.8.dist-info/._SOURCES.txt
pecheny_utils-0.0.8.dist-info/._dependency_links.txt
pecheny_utils-0.0.8.dist-info/._requires.txt
pecheny_utils-0.0.8.dist-info/._top_level.txt
pecheny_utils-0.0.8.dist-info/METADATA
pecheny_utils-0.0.8.dist-info/WHEEL
pecheny_utils-0.0.8.dist-info/top_level.txt
pecheny_utils-0.0.8.dist-info/RECORD
