Metadata-Version: 2.4
Name: pecheny_utils
Version: 0.0.8
Summary: Utils for my projects
Home-page: https://gitlab.com/peczony/pecheny_utils
Author: Alexander Pecheny
Author-email: ap@pecheny.me
Classifier: Programming Language :: Python :: 3
Classifier: License :: OSI Approved :: MIT License
Classifier: Operating System :: OS Independent
Requires-Dist: requests
Dynamic: author
Dynamic: author-email
Dynamic: classifier
Dynamic: description
Dynamic: description-content-type
Dynamic: home-page
Dynamic: requires-dist
Dynamic: summary
